convmoji/__init__.py
convmoji/commit.py
convmoji/commit_types.py
convmoji-0.1.7.dist-info/entry_points.txt
convmoji-0.1.7.dist-info/LICENSE
convmoji-0.1.7.dist-info/WHEEL
convmoji-0.1.7.dist-info/METADATA
convmoji-0.1.7.dist-info/RECORD
