Metadata-Version: 2.1
Name: convmoji
Version: 0.1.7
Summary: A simple cli tool to commit Conventional Commits with emojis.
Home-page: https://github.com/KnowKit/convmoji
License: MIT
Keywords: conventional,commits,emoji,cli,tool
Author: arrrrrmin
Author-email: info@dotarmin.info
Maintainer: arrrrrmin
Maintainer-email: info@dotarmin.info
Requires-Python: >=3.8,<4.0
Classifier: Development Status :: 3 - Alpha
Classifier: Environment :: Console
Classifier: Intended Audience :: Developers
Classifier: License :: OSI Approved :: MIT License
Classifier: Programming Language :: Python :: 3
Classifier: Programming Language :: Python :: 3.10
Classifier: Programming Language :: Python :: 3.8
Classifier: Programming Language :: Python :: 3.9
Classifier: Topic :: Software Development :: Version Control :: Git
Classifier: Topic :: Utilities
Requires-Dist: pydantic (>=1.8.2,<2.0.0)
Requires-Dist: questionary (>=1.10.0,<2.0.0)
Requires-Dist: typer (>=0.4.0,<0.5.0)
Project-URL: Documentation, https://github.com/KnowKit/convmoji
